jumpstarter_cli/__init__.py
jumpstarter_cli/__main__.py
jumpstarter_cli/cli_test.py
jumpstarter_cli/common.py
jumpstarter_cli/common_test.py
jumpstarter_cli/config.py
jumpstarter_cli/config_client.py
jumpstarter_cli/config_exporter.py
jumpstarter_cli/create.py
jumpstarter_cli/delete.py
jumpstarter_cli/get.py
jumpstarter_cli/get_test.py
jumpstarter_cli/j.py
jumpstarter_cli/jmp.py
jumpstarter_cli/login.py
jumpstarter_cli/py.typed
jumpstarter_cli/run.py
jumpstarter_cli/shell.py
jumpstarter_cli/update.py
jumpstarter_cli-0.7.4.dist-info/METADATA
jumpstarter_cli-0.7.4.dist-info/WHEEL
jumpstarter_cli-0.7.4.dist-info/entry_points.txt
jumpstarter_cli-0.7.4.dist-info/RECORD
